netizens/__init__.py
netizens/account.py
netizens/amount.py
netizens/asset.py
netizens/block.py
netizens/blockchain.py
netizens/blockchainobject.py
netizens/committee.py
netizens/dex.py
netizens/exceptions.py
netizens/genesisbalance.py
netizens/htlc.py
netizens/instance.py
netizens/market.py
netizens/memo.py
netizens/message.py
netizens/netizens.py
netizens/notify.py
netizens/price.py
netizens/proposal.py
netizens/storage.py
netizens/transactionbuilder.py
netizens/utils.py
netizens/vesting.py
netizens/wallet.py
netizens/witness.py
netizens/worker.py
netizensapi/__init__.py
netizensapi/exceptions.py
netizensapi/netizensnoderpc.py
netizensapi/websocket.py
netizensbase/__init__.py
netizensbase/account.py
netizensbase/asset_permissions.py
netizensbase/bip38.py
netizensbase/chains.py
netizensbase/memo.py
netizensbase/objects.py
netizensbase/objecttypes.py
netizensbase/operationids.py
netizensbase/operations.py
netizensbase/signedtransactions.py
netizensbase/transactions.py
netizens-0.5.4.dist-info/AUTHORS
netizens-0.5.4.dist-info/LICENSE.txt
netizens-0.5.4.dist-info/METADATA
netizens-0.5.4.dist-info/WHEEL
netizens-0.5.4.dist-info/top_level.txt
netizens-0.5.4.dist-info/RECORD
