Metadata-Version: 2.1
Name: netizens
Version: 0.5.4
Summary: Python library for netizens
Home-page: https://github.com/donbc/python-netizens
Author: Don BC
Author-email: donbc@protonmail.com
Maintainer: Don BC
Maintainer-email: donbc@protonmail.com
License: UNKNOWN
Download-URL: https://github.com/donbc/python-netizens/tarball/0.5.4
Keywords: netizens,library,api,rpc
Platform: UNKNOWN
Classifier: License :: OSI Approved :: MIT License
Classifier: Operating System :: OS Independent
Classifier: Programming Language :: Python :: 3
Classifier: Development Status :: 3 - Alpha
Classifier: Intended Audience :: Developers
Classifier: Intended Audience :: Financial and Insurance Industry
Classifier: Topic :: Office/Business :: Financial
Requires-Dist: graphenelib (>=1.1.16)
Requires-Dist: websockets (==7.0)
Requires-Dist: Events (==0.3)
